futura/__init__.py
futura/constants.py
futura/default_filters.py
futura/markets.py
futura/recipe_parser.py
futura/regionalisation.py
futura/sectors.py
futura/storage.py
futura/technology.py
futura/utils.py
futura/wrappers.py
futura/wurst_monkeypatch.py
futura/assets/lci-Carma-CCS-base-GLO2.xlsx
futura_ui/__init__.py
futura_ui/app/__init__.py
futura_ui/app/application.py
futura_ui/app/controller.py
futura_ui/app/settings.py
futura_ui/app/signals.py
futura_ui/app/models/__init__.py
futura_ui/app/models/treemodel.py
futura_ui/app/ui/__init__.py
futura_ui/app/ui/icons.py
futura_ui/app/ui/main.py
futura_ui/app/ui/style.py
futura_ui/app/ui/utils.py
futura_ui/app/ui/dialogs/__init__.py
futura_ui/app/ui/dialogs/project_choice.py
futura_ui/app/ui/dialogs/run_dialog.py
futura_ui/icons/ab_main/__init__.py
futura_ui/icons/context/__init__.py
futura_ui/icons/metaprocess/__init__.py
futura-0.0.3.dist-info/LICENSE.txt
futura-0.0.3.dist-info/METADATA
futura-0.0.3.dist-info/WHEEL
futura-0.0.3.dist-info/entry_points.txt
futura-0.0.3.dist-info/top_level.txt
futura-0.0.3.dist-info/RECORD
